odoo/addons/stock_picking_send_by_mail/README.rst
odoo/addons/stock_picking_send_by_mail/__init__.py
odoo/addons/stock_picking_send_by_mail/__manifest__.py
odoo/addons/stock_picking_send_by_mail/i18n/de.po
odoo/addons/stock_picking_send_by_mail/i18n/es.po
odoo/addons/stock_picking_send_by_mail/i18n/fr.po
odoo/addons/stock_picking_send_by_mail/i18n/it.po
odoo/addons/stock_picking_send_by_mail/i18n/pt.po
odoo/addons/stock_picking_send_by_mail/i18n/pt_BR.po
odoo/addons/stock_picking_send_by_mail/i18n/stock_picking_send_by_mail.pot
odoo/addons/stock_picking_send_by_mail/models/__init__.py
odoo/addons/stock_picking_send_by_mail/models/stock_picking.py
odoo/addons/stock_picking_send_by_mail/readme/CONTRIBUTORS.md
odoo/addons/stock_picking_send_by_mail/readme/DESCRIPTION.md
odoo/addons/stock_picking_send_by_mail/readme/USAGE.md
odoo/addons/stock_picking_send_by_mail/static/description/icon.png
odoo/addons/stock_picking_send_by_mail/static/description/index.html
odoo/addons/stock_picking_send_by_mail/tests/__init__.py
odoo/addons/stock_picking_send_by_mail/tests/test_stock_picking_send_by_mail.py
odoo/addons/stock_picking_send_by_mail/views/stock_picking_view.xml
odoo_addon_stock_picking_send_by_mail-18.0.1.0.1.dist-info/METADATA
odoo_addon_stock_picking_send_by_mail-18.0.1.0.1.dist-info/WHEEL
odoo_addon_stock_picking_send_by_mail-18.0.1.0.1.dist-info/top_level.txt
odoo_addon_stock_picking_send_by_mail-18.0.1.0.1.dist-info/RECORD
