Metadata-Version: 2.1
Name: odoo-addon-stock_picking_send_by_mail
Version: 18.0.1.0.1
Requires-Python: >=3.10
Requires-Dist: odoo==18.0.*
Summary: Send stock picking by email
Home-page: https://github.com/OCA/stock-logistics-workflow
License: AGPL-3
Author: =?utf-8?q?Sandra_Figueroa_Varela=2C_Tecnativa=2C_Odoo_Community_Association_=28OCA=29=2C_Daniel_Dom=C3=ADnguez_=28Xtendoo=29?=
Author-email: support@odoo-community.org
Classifier: Programming Language :: Python
Classifier: Framework :: Odoo
Classifier: Framework :: Odoo :: 18.0
Classifier: License :: OSI Approved :: GNU Affero General Public License v3
